educelab/globus/__init__.py
educelab/globus/config.py
educelab/globus/login.py
educelab/globus/cp/main.py
educelab_globus-0.1.3.dist-info/licenses/LICENSE
educelab_globus-0.1.3.dist-info/licenses/NOTICE
educelab_globus-0.1.3.dist-info/METADATA
educelab_globus-0.1.3.dist-info/WHEEL
educelab_globus-0.1.3.dist-info/entry_points.txt
educelab_globus-0.1.3.dist-info/top_level.txt
educelab_globus-0.1.3.dist-info/RECORD
