Metadata-Version: 2.4
Name: educelab-globus
Version: 0.1.3
Summary: EduceLab Globus module
Home-page: https://gitlab.com/educelab/educelab-globus
Download-URL: https://gitlab.com/educelab/educelab-globus
Author: Seth Parker
Author-email: c.seth.parker@uky.edu
Classifier: Programming Language :: Python :: 3
Classifier: Programming Language :: Python :: 3.10
Classifier: Programming Language :: Python :: 3.11
Classifier: Programming Language :: Python :: 3.12
Classifier: Operating System :: OS Independent
Classifier: License :: OSI Approved :: GNU Affero General Public License v3
Requires-Python: >=3.10
License-File: LICENSE
License-File: NOTICE
Requires-Dist: globus-sdk>=3.46
Requires-Dist: prompt-toolkit
Requires-Dist: tomli; python_version < "3.11"
Dynamic: download-url
Dynamic: license-file
